unified2
